sploitkit/VERSION.txt
sploitkit/__info__.py
sploitkit/__init__.py
sploitkit/__main__.py
sploitkit/base/__init__.py
sploitkit/base/config.conf
sploitkit/base/commands/__init__.py
sploitkit/base/commands/general.py
sploitkit/base/commands/module.py
sploitkit/base/commands/project.py
sploitkit/base/commands/recording.py
sploitkit/base/commands/root.py
sploitkit/base/commands/session.py
sploitkit/base/commands/utils.py
sploitkit/base/models/__init__.py
sploitkit/base/models/notes.py
sploitkit/base/models/organization.py
sploitkit/base/models/systems.py
sploitkit/base/models/users.py
sploitkit/core/__init__.py
sploitkit/core/application.py
sploitkit/core/command.py
sploitkit/core/console.py
sploitkit/core/entity.py
sploitkit/core/model.py
sploitkit/core/module.py
sploitkit/core/components/__init__.py
sploitkit/core/components/completer.py
sploitkit/core/components/config.py
sploitkit/core/components/defaults.py
sploitkit/core/components/files.py
sploitkit/core/components/jobs.py
sploitkit/core/components/layout.py
sploitkit/core/components/logger.py
sploitkit/core/components/recorder.py
sploitkit/core/components/sessions.py
sploitkit/core/components/store.py
sploitkit/core/components/validator.py
sploitkit-0.6.0.dist-info/LICENSE
sploitkit-0.6.0.dist-info/METADATA
sploitkit-0.6.0.dist-info/WHEEL
sploitkit-0.6.0.dist-info/entry_points.txt
sploitkit-0.6.0.dist-info/top_level.txt
sploitkit-0.6.0.dist-info/RECORD
