Metadata-Version: 2.1
Name: sploitkit
Version: 0.6.0
Summary: Devkit for easilly building Metasploit-like framework consoles
Author-email: Alexandre D'Hondt <alexandre.dhondt@gmail.com>
License: GNU GENERAL PUBLIC LICENSE
Project-URL: documentation, https://python-sploitkit.readthedocs.io/en/latest/?badge=latest
Project-URL: homepage, https://github.com/dhondta/python-sploitkit
Project-URL: issues, https://github.com/dhondta/python-sploitkit/issues
Project-URL: repository, https://github.com/dhondta/python-sploitkit
Keywords: python,development,programming,cli,framework,console,devkit
Classifier: Development Status :: 4 - Beta
Classifier: Environment :: Console
Classifier: Intended Audience :: Developers
Classifier: Intended Audience :: Information Technology
Classifier: License :: OSI Approved :: GNU General Public License v3 or later (GPLv3+)
Classifier: Programming Language :: Python :: 3
Classifier: Programming Language :: Python :: 3.8
Classifier: Programming Language :: Python :: 3.9
Classifier: Programming Language :: Python :: 3.10
Classifier: Programming Language :: Python :: 3.11
Classifier: Programming Language :: Python :: 3.12
Classifier: Topic :: Software Development :: Libraries :: Python Modules
Requires-Python: <4,>=3.8
License-File: LICENSE
Requires-Dist: peewee >=3.17.6
Requires-Dist: prompt-toolkit >=3.0.47
Requires-Dist: requests
Requires-Dist: tinyscript >=1.30.15
